arithmetic_graphing/__init__.py
arithmetic_graphing-0.0.9.dist-info/METADATA
arithmetic_graphing-0.0.9.dist-info/WHEEL
arithmetic_graphing-0.0.9.dist-info/top_level.txt
arithmetic_graphing-0.0.9.dist-info/RECORD
