Metadata-Version: 2.1
Name: arithmetic-graphing
Version: 0.0.9
Summary: A small arithmetic module for functions of graphing
Home-page: UNKNOWN
Author: TheOnlyWalrus
License: MIT
Platform: UNKNOWN
Classifier: Programming Language :: Python :: 3
Classifier: Natural Language :: English
Classifier: Operating System :: OS Independent
Classifier: Development Status :: 1 - Planning
Classifier: Topic :: Education
Classifier: Intended Audience :: Education
